SecurePassX/SecurePassX.py
SecurePassX/__init__.py
SecurePassX/__main__.py
SecurePassX/cli.py
SecurePassX/config.py
SecurePassX/database.py
SecurePassX/security.py
SecurePassX-0.1.0.dist-info/LICENSE
SecurePassX-0.1.0.dist-info/METADATA
SecurePassX-0.1.0.dist-info/WHEEL
SecurePassX-0.1.0.dist-info/entry_points.txt
SecurePassX-0.1.0.dist-info/top_level.txt
SecurePassX-0.1.0.dist-info/RECORD
