Metadata-Version: 2.1
Name: SecurePassX
Version: 0.1.0
Summary: A secure password management solution
Author: Anurag
Author-email: kvanurag39@gmail.com
License-File: LICENSE
Requires-Dist: cryptography ==43.0.1
Requires-Dist: pytest ==8.3.3
Requires-Dist: typer ==0.12.5
Requires-Dist: typing-extensions ==4.12.2
